mc_games/__init__.py
mc_games/mc_raiden.py
mc_games/images/bg.jpg
mc_games/images/bg1.jpg
mc_games/images/bg2.jpg
mc_games/images/bg3.jpg
mc_games/images/bg4.jpg
mc_games/images/bg5.jpg
mc_games/images/boom-1.png
mc_games/images/boom-2.png
mc_games/images/boom-3.png
mc_games/images/boom-4.png
mc_games/images/boom-5.png
mc_games/images/boom-6.png
mc_games/images/boom-7.png
mc_games/images/bullet-1.png
mc_games/images/bullet-2.png
mc_games/images/e1.png
mc_games/images/e2.png
mc_games/images/p1.png
mc_games/music/bgm.mp3
mc_games/sounds/boom.wav
mc_games-0.6.dist-info/LICENSE
mc_games-0.6.dist-info/METADATA
mc_games-0.6.dist-info/WHEEL
mc_games-0.6.dist-info/entry_points.txt
mc_games-0.6.dist-info/top_level.txt
mc_games-0.6.dist-info/RECORD
